{
  "display": {
    "icon": {
      "item": "minecraft:warped_fungus_on_a_stick",
      "nbt": "{CustomModelData:14}"
    },
    "title": {
      "translate": "advancements.alien-packs.rm_portal_gun.fill_portal_gun.title"
    },
    "description": {
      "translate": "advancements.alien-packs.rm_portal_gun.fill_portal_gun.description"
    },
    "frame": "goal",
    "show_toast": true,
    "announce_to_chat": false,
    "hidden": false
  },
  "parent": "ap-rm_portal_gun:portal_gun/repair_portal_gun",
  "criteria": {
    "fill_portal_gun_03": {
      "trigger": "minecraft:inventory_changed",
      "conditions": {
        "items": [
          {
            "items": [
              "minecraft:warped_fungus_on_a_stick"
            ],
            "nbt": "{RMPortalGun:1b,RMFuelLevel:3b}"
          }
        ]
      }
    },
    "fill_portal_gun_02": {
      "trigger": "minecraft:inventory_changed",
      "conditions": {
        "items": [
          {
            "items": [
              "minecraft:warped_fungus_on_a_stick"
            ],
            "nbt": "{RMPortalGun:1b,RMFuelLevel:2b}"
          }
        ]
      }
    },
    "fill_portal_gun_01": {
      "trigger": "minecraft:inventory_changed",
      "conditions": {
        "items": [
          {
            "items": [
              "minecraft:warped_fungus_on_a_stick"
            ],
            "nbt": "{RMPortalGun:1b,RMFuelLevel:1b}"
          }
        ]
      }
    }
  },
  "requirements": [
    [
      "fill_portal_gun_03",
      "fill_portal_gun_02",
      "fill_portal_gun_01"
    ]
  ]
}
