[
  {
    "condition": "minecraft:reference",
    "name": "ap-rm_portal_gun:portal_gun/ricks_gun/texture"
  },
  {
    "condition": "minecraft:entity_scores",
    "entity": "this",
    "scores": {
      "ap-rm_portal_click": {
        "min": 1
      }
    }
  },
  {
    "condition": "minecraft:inverted",
    "term": {
      "condition": "minecraft:entity_properties",
      "entity": "this",
      "predicate": {
        "nbt": "{SelectedItem:{tag:{RMFuelLevel:0b}}}"
      }
    }
  },
  {
    "condition": "minecraft:entity_properties",
    "entity": "this",
    "predicate": {
      "nbt": "{SelectedItem:{tag:{RMPortalGun:3b}}}"
    }
  }
]
